README.rst
setup.py
tests/__init__.py
tests/test_api.py
uq/__init__.py
uq/client.py
uq/conn.py
uq/consts.py
uq/duration.py
uq/exceptions.py
uq/mc_mock.py
uq/utils.py
uq/version.py
uq.egg-info/PKG-INFO
uq.egg-info/SOURCES.txt
uq.egg-info/dependency_links.txt
uq.egg-info/requires.txt
uq.egg-info/top_level.txt