Metadata-Version: 1.0
Name: uq
Version: 0.1.2
Summary: Python library for uq cluster
Home-page: http://github.com/amyangfei/pyuq
Author: Yang Fei
Author-email: amyangfei@gmail.com
License: MIT
Keywords: Uq,message queue
Platform: UNKNOWN
